dtsp/__init__.py
dtsp/metrics.py
dtsp/param.py
dtsp/plot.py
dtsp/record.py
dtsp/utils.py
dtsp/dataset/__init__.py
dtsp/dataset/curve.py
dtsp/dataset/data.csv
dtsp/dataset/dataset.py
dtsp/dataset/example_data.csv
dtsp/dataset/example_datasets.py
dtsp/dataset/utils.py
dtsp/models/__init__.py
dtsp/models/base_model.py
dtsp/models/move_scale.py
dtsp/models/seq2seq.py
dtsp/models/simple_seq2seq.py
dtsp/models/simple_wavenet.py
dtsp/models/wavenet.py
dtsp/modules/__init__.py
dtsp/modules/attention.py
dtsp/modules/causal_conv.py
dtsp/modules/decoder.py
dtsp/modules/embeddings.py
dtsp/modules/encoder.py
dtsp/modules/transformer.py
dtsp-0.3.1.dist-info/METADATA
dtsp-0.3.1.dist-info/WHEEL
dtsp-0.3.1.dist-info/top_level.txt
dtsp-0.3.1.dist-info/RECORD
