Metadata-Version: 2.1
Name: dtsp
Version: 0.3.1
Summary: DeepLearning for Time Series Prediction Library
Home-page: https://github.com/EvilPsyCHo/competition
Author: zhirui zhou
Author-email: evilpsycho42@gmail.com
License: Apache 2.0
Platform: UNKNOWN
